refinenet/__init__.py
refinenet/__main__.py
refinenet/evaluator.py
refinenet/helpers.py
refinenet/predictor.py
refinenet/refinenet.py
refinenet/trainer.py
refinenet/datasets/__init__.py
refinenet/datasets/coco.py
refinenet/datasets/helpers.py
refinenet/datasets/nyu.py
refinenet/datasets/sbd.py
refinenet/datasets/voc.py
refinenet/models/__init__.py
refinenet/models/blocks.py
refinenet/models/helpers.py
refinenet/models/refinenet.py
refinenet/models/refinenet_lw.py
refinenet-0.9.5.dist-info/LICENSE.txt
refinenet-0.9.5.dist-info/METADATA
refinenet-0.9.5.dist-info/WHEEL
refinenet-0.9.5.dist-info/entry_points.txt
refinenet-0.9.5.dist-info/top_level.txt
refinenet-0.9.5.dist-info/RECORD
