Metadata-Version: 2.1
Name: refinenet
Version: 0.9.5
Summary: RefineNet semantic image segmentation
Home-page: https://github.com/best-of-acrv/refinenet
Author: Ben Talbot
Author-email: b.talbot@qut.edu.au
License: UNKNOWN
Platform: UNKNOWN
Classifier: Development Status :: 4 - Beta
Classifier: Programming Language :: Python :: 3
Classifier: License :: OSI Approved :: BSD License
Classifier: Operating System :: OS Independent
License-File: LICENSE.txt
Requires-Dist: acrv-datasets
Requires-Dist: numpy
Requires-Dist: pillow
Requires-Dist: pycocotools
Requires-Dist: scipy
Requires-Dist: six
Requires-Dist: torch
Requires-Dist: torchvision
